[
  {
    "Name": "dilbert.com",
    "Url": "http://dilbert.com",
    "Path": "^/strip/((?:[0-9]+-?)+$",
    "Images": [
      {
        "Type": "Attribute",
        "AttributeName": "src",
        "Selector": ".img-comic"
      }
    ],
    "FileNameFragments": [
      {
        "Type": "Text",
        "Selector": "title",
        "PatternString": "^.*?-  Dilbert Comic Strip on (\\d{4}-\\d{2}-\\d{2}).*$"
      },
      {
        "Type": "Text",
        "Selector": ".comic-title-name"
      }
    ],
    "FileNameFragmentDelimiter": "_-_"
  },
  {
    "Name": "www.schisslaweng.net",
    "Url": "https://www.schisslaweng.net",
    "Path": "^/(.*?)/.*$",
    "Images": [
      {
        "Type": "Attribute",
        "AttributeName": "src",
        "Selector": ".gallery-item img"
      }
    ],
    "FileNameFragments": [
      {
        "Type": "Attribute",
        "AttributeName": "content",
        "Selector": "meta[name=\"shareaholic:article_published_time\"]",
        "PatternString": "^(\\d{4}-\\d{2}-\\d{2}).*$"
      },
      {
        "Type": "Text",
        "Selector": "h1"
      }
    ],
    "FileNameFragmentDelimiter": "_-_"
  }
] 